mcpx_pydantic_ai.py
mcpx_pydantic_ai-0.7.0.dist-info/METADATA
mcpx_pydantic_ai-0.7.0.dist-info/WHEEL
mcpx_pydantic_ai-0.7.0.dist-info/top_level.txt
mcpx_pydantic_ai-0.7.0.dist-info/RECORD
