Metadata-Version: 2.4
Name: mcpx-pydantic-ai
Version: 0.7.0
Summary: Pydantic Agent with mcp.run tools
Requires-Python: >=3.12
Requires-Dist: mcp-run>=0.5.0
Requires-Dist: pydantic>=2.10.4
Requires-Dist: pydantic-ai>=0.0.35
